eflips/opt/__init__.py
eflips/opt/depot_rotation_matching.py
eflips/opt/py.typed
eflips/opt/scheduling/__init__.py
eflips/opt/scheduling/util.py
eflips/opt/smart_charging.py
eflips/opt/util.py
eflips_opt-0.3.19.dist-info/METADATA
eflips_opt-0.3.19.dist-info/WHEEL
eflips_opt-0.3.19.dist-info/licenses/LICENSE
eflips_opt-0.3.19.dist-info/RECORD
