Metadata-Version: 2.4
Name: eflips-opt
Version: 0.3.19
Summary: A collection of pre-simulation optimization algorithms for eFLIPS.
License: AGPLV3.md
License-File: LICENSE
Author: Ludger Heide
Author-email: ludger.heide@tu-berlin.de
Requires-Python: >=3.10, <3.14
Classifier: License :: Other/Proprietary License
Classifier: Programming Language :: Python :: 3
Classifier: Programming Language :: Python :: 3.10
Classifier: Programming Language :: Python :: 3.11
Classifier: Programming Language :: Python :: 3.12
Classifier: Programming Language :: Python :: 3.13
Requires-Dist: dash-cytoscape (>=1.0.2,<2.0)
Requires-Dist: eflips-model (>=10.0.3,<11.0.0)
Requires-Dist: eflips-schedule-rust (>=2.0.1,<3.0)
Requires-Dist: gurobipy (>=12.0.1,<13.0)
Requires-Dist: kaleido (==0.2.1)
Requires-Dist: networkx (>=3.3,<4.0)
Requires-Dist: numpy (>=1.26.4,<3.0)
Requires-Dist: openrouteservice (>=2.3.3,<3.0)
Requires-Dist: pandas (>=2.1,<3.0)
Requires-Dist: plotly (>=5.22.0,<6.0)
Requires-Dist: polyline (>=2.0.3,<3.0.0)
Requires-Dist: pyomo (>=6.7.1,<7.0)
Requires-Dist: scipy (>=1.14.0,<2.0)
Requires-Dist: shapely (>=2.0.3,<3.0)
Requires-Dist: tqdm (>=4.66.4,<5.0)
Project-URL: Repository, https://github.com/mpm-tu-berlin/eflips-opt
